biblebot/__init__.py
biblebot/__version__.py
biblebot/exceptions.py
biblebot/api/__init__.py
biblebot/api/_mileage.py
biblebot/api/base.py
biblebot/api/common.py
biblebot/api/intranet.py
biblebot/api/kbu.py
biblebot/api/library.py
biblebot/api/lms.py
biblebot/api/mileage.py
biblebot/reqeust/__init__.py
biblebot/reqeust/aiohttp_conn.py
biblebot/reqeust/base.py
biblebot/reqeust/requests_conn.py
biblebot-0.4.3.dist-info/LICENSE
biblebot-0.4.3.dist-info/METADATA
biblebot-0.4.3.dist-info/WHEEL
biblebot-0.4.3.dist-info/top_level.txt
biblebot-0.4.3.dist-info/RECORD
