Metadata-Version: 2.1
Name: biblebot
Version: 0.4.3
Summary: Scraper for KBU students
Home-page: https://github.com/rekyungmin/biblebot-scraper
Author: Kyungmin Lee
Author-email: rekyungmin@gmail.com
Maintainer: Kyungmin Lee <rekyungmin@gmail.com>, Yongki Kim <ygflove@likelion.org>
License: UNKNOWN
Platform: UNKNOWN
Classifier: License :: OSI Approved :: MIT License
Classifier: Development Status :: 5 - Production/Stable
Classifier: Intended Audience :: Developers
Classifier: Programming Language :: Python :: 3
Classifier: Programming Language :: Python :: 3.7
Requires-Python: >=3.7
License-File: LICENSE
Requires-Dist: beautifulsoup4 (>=4.8.0)
Provides-Extra: http
Requires-Dist: aiohttp[speedups] (>=3.6.2) ; extra == 'http'
